bpkio_api/__init__.py
bpkio_api/api.py
bpkio_api/caching.py
bpkio_api/constants.py
bpkio_api/consumer.py
bpkio_api/credential_provider.py
bpkio_api/defaults.py
bpkio_api/endpoints/__init__.py
bpkio_api/endpoints/categories.py
bpkio_api/endpoints/consumption.py
bpkio_api/endpoints/login.py
bpkio_api/endpoints/services.py
bpkio_api/endpoints/sources.py
bpkio_api/endpoints/tenants.py
bpkio_api/endpoints/transcoding_profiles.py
bpkio_api/endpoints/users.py
bpkio_api/exceptions.py
bpkio_api/helpers/fuzzy_properties.py
bpkio_api/helpers/list.py
bpkio_api/helpers/objects.py
bpkio_api/helpers/recorder/__init__.py
bpkio_api/helpers/recorder/curl.py
bpkio_api/helpers/recorder/exporter.py
bpkio_api/helpers/recorder/markdown.py
bpkio_api/helpers/recorder/postman.py
bpkio_api/helpers/recorder/session_items.py
bpkio_api/helpers/recorder/session_recorder.py
bpkio_api/helpers/recorder/text.py
bpkio_api/helpers/search.py
bpkio_api/helpers/source_type.py
bpkio_api/helpers/times.py
bpkio_api/helpers/upsert.py
bpkio_api/mappings.py
bpkio_api/models/BkpioSession.py
bpkio_api/models/Categories.py
bpkio_api/models/Consumption.py
bpkio_api/models/Login.py
bpkio_api/models/Services.py
bpkio_api/models/Slots.py
bpkio_api/models/Sources.py
bpkio_api/models/Tenants.py
bpkio_api/models/TranscodingProfiles.py
bpkio_api/models/Users.py
bpkio_api/models/__init__.py
bpkio_api/models/common.py
bpkio_api/models/model_graph.py
bpkio_api/response_handler.py
bpkio_api/tenant_profile.py
bpkio_python_sdk-3.1.0.dist-info/METADATA
bpkio_python_sdk-3.1.0.dist-info/WHEEL
bpkio_python_sdk-3.1.0.dist-info/licenses/LICENSE.md
bpkio_python_sdk-3.1.0.dist-info/RECORD
