Metadata-Version: 2.4
Name: bpkio-python-sdk
Version: 3.1.0
Summary: An (opinionated) Python SDK for the broadpeak.io REST APIs
License-File: LICENSE.md
Author: Fabre Lambeau
Author-email: fabre.lambeau@broadpeak.tv
Requires-Python: >=3.10,<3.14
Classifier: Programming Language :: Python :: 3
Classifier: Programming Language :: Python :: 3.10
Classifier: Programming Language :: Python :: 3.11
Classifier: Programming Language :: Python :: 3.12
Classifier: Programming Language :: Python :: 3.13
Requires-Dist: diskcache (>=5.4.0,<6.0.0)
Requires-Dist: loguru (>=0.7.2,<0.8.0)
Requires-Dist: media-muncher (>=2.0.0,<3.0.0)
Requires-Dist: mpd-inspector (>=1.2.1,<2.0.0)
Requires-Dist: pydantic (>=2.12.0,<3.0.0)
Requires-Dist: pytz (>=2023.3,<2024.0)
Requires-Dist: setuptools (>=67.6.1,<68.0.0)
Requires-Dist: uplink (>=0.10.0,<0.11.0)
